set_pip_mirror/__init__.py
set_pip_mirror/set_pip_mirror.py
set_pip_mirror-1.5.15.dist-info/LICENSE
set_pip_mirror-1.5.15.dist-info/METADATA
set_pip_mirror-1.5.15.dist-info/WHEEL
set_pip_mirror-1.5.15.dist-info/top_level.txt
set_pip_mirror-1.5.15.dist-info/RECORD
