Metadata-Version: 2.1
Name: set-pip-mirror
Version: 1.5.15
Summary: set pip mirror to tsinghua
Home-page: https://github.com/sylan215/set_pip_mirror
Author: sylan215
Author-email: sylan215@163.com
License: MIT License
Classifier: License :: OSI Approved :: MIT License
Classifier: Programming Language :: Python :: 3
Classifier: Programming Language :: Python :: 3.7
Classifier: Programming Language :: Python :: 3.8
Classifier: Programming Language :: Python :: 3.9
Classifier: Programming Language :: Python :: 3.10
Classifier: Programming Language :: Python :: 3.11
Classifier: Programming Language :: Python :: 3.12
Classifier: Programming Language :: Python :: 3.13
License-File: LICENSE
